pyHTTPInterface/Exceptions.py
pyHTTPInterface/HTTPRequestHandler.py
pyHTTPInterface/Request.py
pyHTTPInterface/Response.py
pyHTTPInterface/__init__.py
pyHTTPInterface-0.1.4.dist-info/LICENSE.md
pyHTTPInterface-0.1.4.dist-info/METADATA
pyHTTPInterface-0.1.4.dist-info/WHEEL
pyHTTPInterface-0.1.4.dist-info/top_level.txt
pyHTTPInterface-0.1.4.dist-info/RECORD
